aps_toolkit/AECDataModel.py
aps_toolkit/Auth.py
aps_toolkit/AuthGoogleColab.py
aps_toolkit/BIM360.py
aps_toolkit/Bucket.py
aps_toolkit/ConvertUtils.py
aps_toolkit/DbReader.py
aps_toolkit/Derivative.py
aps_toolkit/Fragments.py
aps_toolkit/InputStream.py
aps_toolkit/ManifestItem.py
aps_toolkit/MaterialProperties.py
aps_toolkit/Materials.py
aps_toolkit/PackFileReader.py
aps_toolkit/PathInfo.py
aps_toolkit/ProDbReaderCad.py
aps_toolkit/ProDbReaderNavis.py
aps_toolkit/ProDbReaderRevit.py
aps_toolkit/PropReader.py
aps_toolkit/Resource.py
aps_toolkit/SVFContent.py
aps_toolkit/SVFGeometries.py
aps_toolkit/SVFImage.py
aps_toolkit/SVFLines.py
aps_toolkit/SVFManifestType.py
aps_toolkit/SVFMaterialGroup.py
aps_toolkit/SVFMaterialMap.py
aps_toolkit/SVFMaterialMapScale.py
aps_toolkit/SVFMaterials.py
aps_toolkit/SVFMesh.py
aps_toolkit/SVFMetadata.py
aps_toolkit/SVFPoints.py
aps_toolkit/SVFReader.py
aps_toolkit/SVFTransform.py
aps_toolkit/SVFUVMap.py
aps_toolkit/Token.py
aps_toolkit/Webhooks.py
aps_toolkit/__init__.py
aps_toolkit/units/DisplayUnits.py
aps_toolkit/units/__init__.py
aps_toolkit/units/units.json
aps_toolkit-1.1.9.data/data/aps_toolkit/units/units.json
test/__init__.py
test/context.py
test/test_Webhooks.py
test/test_aec_data_model.py
test/test_auth.py
test/test_auth_colab.py
test/test_bim360.py
test/test_bucket.py
test/test_db_reader.py
test/test_derivative.py
test/test_fragment.py
test/test_geometries.py
test/test_image.py
test/test_material.py
test/test_mesh.py
test/test_metadata.py
test/test_prop_reader.py
test/test_prop_reader_cad.py
test/test_prop_reader_navis.py
test/test_prop_reader_revit.py
test/test_svf_reader.py
test/test_token.py
aps_toolkit-1.1.9.dist-info/METADATA
aps_toolkit-1.1.9.dist-info/WHEEL
aps_toolkit-1.1.9.dist-info/top_level.txt
aps_toolkit-1.1.9.dist-info/RECORD
