Metadata-Version: 2.1
Name: aps-toolkit
Version: 1.1.9
Summary: A Toolkit Autodesk Platform Services for Python
Home-page: https://github.com/chuongmep/aps-toolkit
Author: chuong mep
Author-email: chuongpqvn@gmail.com
Project-URL: Bug Tracker, https://github.com/chuongmep/aps-toolkit/issues
Classifier: Programming Language :: Python :: 3
Classifier: License :: OSI Approved :: GNU Affero General Public License v3
Classifier: Operating System :: OS Independent
Requires-Python: >=3.9
Requires-Dist: requests
Requires-Dist: pandas
